{
    "gameSettings": {
        "BET_AMOUNT": 1000,
        "JACKPOT_THRESHOLD": 500000,
        "BET_STOP": 10000,
        "TIME_SEND_MESS": 1,
        "IS_MARTINGALE": false,
        "RATE_MARTINGALE": 2,
        "ZOMBIE": true
    },
    "gameRules": [
        "Nếu 3 viên xúc xắc ra cùng một số (bộ ba đồng nhất), kết quả là BÃO và nhà cái thắng (người chơi thua cược TÀI/XỈU).",
        "Tổng điểm từ 11 đến 17 là TÀI.",
        "Tổng điểm từ 4 đến 10 là XỈU.",
        "Trò chơi dựa trên kết quả của 3 viên xúc xắc."
    ],
    "bettingRules": [
        {
            "betOn": "PURPLE",
            "priority": 10,
            "active": true,
            "description": "RED → PINK → WHITE cược PURPLE.",
            "betAmount": 5000,
            "pattern": [
                "RED",
                "PINK",
                "WHITE"
            ]
        },
        {
            "betOn": [
                "RED",
                "BLUE",
                "PINK"
            ],
            "priority": 0,
            "active": true,
            "description": "Default rule: nếu không khớp pattern nào thì cược RED + BLUE + PINK.",
            "betAmount": [
                1000,
                2000,
                500
            ],
            "pattern": []
        }
    ]
}